{
    "code": {
        "languages": [
            {
                "name": "html",
                "mediaType": "img",
                "filePath": "skills/html",
                "fileExtension": "svg",
                "alt": "html"
            },
            {
                "name": "css",
                "mediaType": "img",
                "filePath": "skills/css",
                "fileExtension": "svg",
                "alt": "css"
            },
            {
                "name": "js",
                "mediaType": "img",
                "filePath": "skills/js",
                "fileExtension": "svg",
                "alt": "js"
            },
            {
                "name": "php",
                "mediaType": "img",
                "filePath": "skills/php",
                "fileExtension": "svg",
                "alt": "php"
            }
        ],
        "frameworks": [
            {
                "name": "astro",
                "mediaType": "img",
                "filePath": "skills/astro",
                "fileExtension": "svg",
                "alt": "astro"
            },
            {
                "name": "react",
                "mediaType": "img",
                "filePath": "skills/react",
                "fileExtension": "svg",
                "alt": "react"
            }
        ],
        "libraries": [
            {
                "name": "p5",
                "mediaType": "img",
                "filePath": "skills/p5",
                "fileExtension": "svg",
                "alt": "p5"
            },
            {
                "name": "gsap",
                "mediaType": "img",
                "filePath": "skills/gsap",
                "fileExtension": "svg",
                "alt": "gsap"
            },
            {
                "name": "ml5",
                "mediaType": "img",
                "filePath": "skills/ml5",
                "fileExtension": "svg",
                "alt": "ml5"
            },
            {
                "name": "strapi",
                "mediaType": "img",
                "filePath": "skills/strapi",
                "fileExtension": "svg",
                "alt": "strapi"
            }
        ],
        "other": [
            {
                "name": "arduino",
                "mediaType": "img",
                "filePath": "skills/arduino",
                "fileExtension": "svg",
                "alt": "arduino"
            }
        ]
    },
    "design": {
        "tools": [
            {
                "name": "illustrator",
                "mediaType": "img",
                "filePath": "skills/illustrator",
                "fileExtension": "svg",
                "alt": "illustrator"
            },
            {
                "name": "photoshop",
                "mediaType": "img",
                "filePath": "skills/photoshop",
                "fileExtension": "svg",
                "alt": "photoshop"
            },
            {
                "name": "after effects",
                "mediaType": "img",
                "filePath": "skills/after-effects",
                "fileExtension": "svg",
                "alt": "after effects"
            },
            {
                "name": "figma",
                "mediaType": "img",
                "filePath": "skills/figma",
                "fileExtension": "svg",
                "alt": "figma"
            }
        ],
        "design skills": [
            {
                "mediaType": null,
                "name": "web / app design"
            },
            {
                "mediaType": null,
                "name": "motion design"
            },
            {
                "mediaType": null,
                "name": "storytelling"
            }
        ],
        "branding": [
            {
                "mediaType": null,
                "name": "brand identity"
            },
            {
                "mediaType": null,
                "name": "logotypes"
            },
            {
                "mediaType": null,
                "name": "iconography"
            }
        ]
    }
}